function_pipe/__init__.py
function_pipe/core/__init__.py
function_pipe/core/function_pipe.py
function_pipe/test/__init__.py
function_pipe/test/test_function_pipe.py
function_pipe-2.1.1.dist-info/LICENSE.txt
function_pipe-2.1.1.dist-info/METADATA
function_pipe-2.1.1.dist-info/WHEEL
function_pipe-2.1.1.dist-info/top_level.txt
function_pipe-2.1.1.dist-info/RECORD
