Metadata-Version: 2.1
Name: function-pipe
Version: 2.1.1
Summary: Tools for extended function composition and pipelines
Home-page: https://github.com/InvestmentSystems/function-pipe
Author: Christopher Ariza, Charles Burkland
Author-email: UNKNOWN
License: MIT
Keywords: functionnode pipenode composition pipeline pipe
Platform: UNKNOWN
Classifier: Development Status :: 5 - Production/Stable
Classifier: Intended Audience :: Developers
Classifier: Topic :: Software Development
Classifier: License :: OSI Approved :: MIT License
Classifier: Programming Language :: Python :: 3.7
Classifier: Programming Language :: Python :: 3.8
Classifier: Programming Language :: Python :: 3.9
